analogio.py
bitbangio.py
board.py
busio.py
digitalio.py
keypad.py
micropython.py
neopixel_write.py
onewireio.py
pulseio.py
pwmio.py
rainbowio.py
usb_hid.py
adafruit_blinka/__init__.py
adafruit_blinka/agnostic/__init__.py
adafruit_blinka/agnostic/time.py
adafruit_blinka/board/OLIMEX_LIME2.py
adafruit_blinka/board/__init__.py
adafruit_blinka/board/binho_nova.py
adafruit_blinka/board/clockworkcpi3.py
adafruit_blinka/board/coral_dev_board.py
adafruit_blinka/board/coral_dev_board_mini.py
adafruit_blinka/board/dragonboard_410c.py
adafruit_blinka/board/feather_can_u2if.py
adafruit_blinka/board/feather_epd_u2if.py
adafruit_blinka/board/feather_huzzah.py
adafruit_blinka/board/feather_rfm_u2if.py
adafruit_blinka/board/feather_u2if.py
adafruit_blinka/board/ftdi_ft2232h.py
adafruit_blinka/board/ftdi_ft232h.py
adafruit_blinka/board/generic_linux_pc.py
adafruit_blinka/board/giantboard.py
adafruit_blinka/board/greatfet_one.py
adafruit_blinka/board/hifive_unleashed.py
adafruit_blinka/board/itsybitsy_u2if.py
adafruit_blinka/board/kb2040_u2if.py
adafruit_blinka/board/lichee_rv.py
adafruit_blinka/board/macropad_u2if.py
adafruit_blinka/board/microchip_mcp2221.py
adafruit_blinka/board/nodemcu.py
adafruit_blinka/board/pico_u2if.py
adafruit_blinka/board/pine64.py
adafruit_blinka/board/pineH64.py
adafruit_blinka/board/pyboard.py
adafruit_blinka/board/qt2040_trinkey_u2if.py
adafruit_blinka/board/qtpy_u2if.py
adafruit_blinka/board/soPine.py
adafruit_blinka/board/tritium-h3.py
adafruit_blinka/board/udoo_x86ultra.py
adafruit_blinka/board/x86j41x5.py
adafruit_blinka/board/bananapi/__init__.py
adafruit_blinka/board/bananapi/bpim2plus.py
adafruit_blinka/board/bananapi/bpim2zero.py
adafruit_blinka/board/bananapi/bpim5.py
adafruit_blinka/board/beagleboard/__init__.py
adafruit_blinka/board/beagleboard/beaglebone_ai.py
adafruit_blinka/board/beagleboard/beaglebone_black.py
adafruit_blinka/board/beagleboard/beaglebone_blue.py
adafruit_blinka/board/beagleboard/beaglebone_pocketbeagle.py
quax_blinka-8.31.0.dist-info/licenses/LICENSE
quax_blinka-8.31.0.dist-info/METADATA
quax_blinka-8.31.0.dist-info/WHEEL
quax_blinka-8.31.0.dist-info/top_level.txt
quax_blinka-8.31.0.dist-info/RECORD
