Metadata-Version: 2.4
Name: quax-Blinka
Version: 8.31.0
Summary: CircuitPython APIs for non-CircuitPython versions of Python such as CPython on Linux and MicroPython.
Home-page: https://github.com/quaxalber/Adafruit_Blinka
Author: Adafruit Industries
Author-email: circuitpython@adafruit.com
License: MIT
Classifier: License :: OSI Approved :: MIT License
Classifier: Programming Language :: Python
Classifier: Programming Language :: Python :: 3
Classifier: Programming Language :: Python :: 3.7
Classifier: Programming Language :: Python :: Implementation :: MicroPython
Requires-Python: >=3.7.0
License-File: LICENSE
Requires-Dist: Adafruit-PlatformDetect>=3.53.0
Requires-Dist: Adafruit-PureIO>=1.1.7
Requires-Dist: pyftdi>=0.40.0
Requires-Dist: adafruit-circuitpython-typing
Dynamic: author
Dynamic: author-email
Dynamic: classifier
Dynamic: description
Dynamic: description-content-type
Dynamic: home-page
Dynamic: license
Dynamic: license-file
Dynamic: requires-dist
Dynamic: requires-python
Dynamic: summary
